{
	"configurations" : 
	[
		{
			"directories" : 
			[
				{
					"build" : ".",
					"jsonFile" : "directory-.-Debug-f5ebdc15457944623624.json",
					"minimumCMakeVersion" : 
					{
						"string" : "3.28"
					},
					"projectIndex" : 0,
					"source" : ".",
					"targetIndexes" : 
					[
						0
					]
				}
			],
			"name" : "Debug",
			"projects" : 
			[
				{
					"directoryIndexes" : 
					[
						0
					],
					"name" : "Extended_Shapes_Blackboard",
					"targetIndexes" : 
					[
						0
					]
				}
			],
			"targets" : 
			[
				{
					"directoryIndex" : 0,
					"id" : "Extended_Shapes_Blackboard::@6890427a1f51a3e7e1df",
					"jsonFile" : "target-Extended_Shapes_Blackboard-Debug-ebfe3f50eb0bc5550cac.json",
					"name" : "Extended_Shapes_Blackboard",
					"projectIndex" : 0
				}
			]
		}
	],
	"kind" : "codemodel",
	"paths" : 
	{
		"build" : "/Users/anastasia_d/CLionProjects/Extended-Shapes-Blackboard/cmake-build-debug",
		"source" : "/Users/anastasia_d/CLionProjects/Extended-Shapes-Blackboard"
	},
	"version" : 
	{
		"major" : 2,
		"minor" : 6
	}
}
